garf/exporter/__init__.py
garf/exporter/collector.py
garf/exporter/exporter.py
garf/exporter/exporter_service.py
garf/exporter/telemetry.py
garf/exporter/entrypoints/__init__.py
garf/exporter/entrypoints/cli.py
garf/exporter/entrypoints/tracer.py
garf_exporter/__init__.py
garf_exporter/collector.py
garf_exporter/exporter.py
garf_exporter/exporter_service.py
garf_exporter/telemetry.py
garf_exporter/entrypoints/__init__.py
garf_exporter/entrypoints/cli.py
garf_exporter/entrypoints/tracer.py
garf_exporter-1.0.0.dist-info/METADATA
garf_exporter-1.0.0.dist-info/WHEEL
garf_exporter-1.0.0.dist-info/entry_points.txt
garf_exporter-1.0.0.dist-info/top_level.txt
garf_exporter-1.0.0.dist-info/RECORD
